socotra_datamart_reports/__init__.py
socotra_datamart_reports/platform_all_policies_report.py
socotra_datamart_reports/platform_financial_transactions_report.py
socotra_datamart_reports/platform_on_risk_report.py
socotra_datamart_reports/transaction_financial_impact_report.py
socotra_datamart_reports/lib/__init__.py
socotra_datamart_reports/lib/base_report.py
socotra_datamart_reports/lib/get_flattened_fields.py
socotra_datamart_reports/lib/queries.py
socotra_datamart_reports-0.0.3.dist-info/LICENSE
socotra_datamart_reports-0.0.3.dist-info/METADATA
socotra_datamart_reports-0.0.3.dist-info/WHEEL
socotra_datamart_reports-0.0.3.dist-info/top_level.txt
socotra_datamart_reports-0.0.3.dist-info/RECORD
