Metadata-Version: 2.1
Name: socotra-datamart-reports
Version: 0.0.3
Summary: Convenience functions for typical reports run against Socotra Data Mart
Home-page: https://docs.socotra.com/production/data/datamartguide.html
Author-email: "Mark Szymanski" <mark.szymanski@socotra.com>
License: MIT
Classifier: License :: OSI Approved :: MIT License
License-File: LICENSE
Requires-Dist: mysql-connector-python (>=8.0)
